LICENSE
MANIFEST.in
README.md
setup.cfg
setup.py
licenser/__init__.py
licenser/__main__.py
licenser/licenser.py
licenser.egg-info/PKG-INFO
licenser.egg-info/SOURCES.txt
licenser.egg-info/dependency_links.txt
licenser.egg-info/entry_points.txt
licenser.egg-info/top_level.txt
licenser/assets/agpl-3.0
licenser/assets/all-rights-reserved
licenser/assets/apache-2.0
licenser/assets/bsd-2-clause
licenser/assets/bsd-3-clause
licenser/assets/epl-1.0
licenser/assets/gpl-2.0
licenser/assets/gpl-3.0
licenser/assets/isc
licenser/assets/mit
licenser/assets/mpl-2.0
licenser/assets/unlicense