Metadata-Version: 1.1
Name: licenser
Version: 2.1.2
Summary: Tool for adding open source licenses to your projects
Home-page: http://github.com/tylucaskelley/licenser
Author: Ty-Lucas Kelley
Author-email: tylucaskelley@gmail.com
License: MIT
Keywords: cli,license,tools,script
Platform: UNKNOWN
Classifier: Development Status :: 5 - Production/Stable
Classifier: Intended Audience :: Developers
Classifier: Natural Language :: English
Classifier: License :: OSI Approved :: MIT License
Classifier: Operating System :: MacOS :: MacOS X
Classifier: Operating System :: POSIX :: Linux
Classifier: Programming Language :: Python
Classifier: Programming Language :: Python :: 2.6
Classifier: Programming Language :: Python :: 2.7
Classifier: Programming Language :: Python :: 3.4
Classifier: Programming Language :: Python :: 3.5
Classifier: Programming Language :: Python :: 3.6
Classifier: Topic :: Software Development :: Libraries :: Python Modules
Classifier: Topic :: Utilities
